
{
    "users": [
        {
            "userId": 0,
            "firstName": "John",
            "lastName": "Doe",
            "doctors": [0, 1, 2, 3],
            "healthData": {
                "caloriesBurned": [
                    {
                        "calories": 100,
                        "date": "2024-02-11T03:30:00.000Z"
                    },
                    {
                        "calories": 100,
                        "date": "2024-02-11T03:30:00.000Z"
                    }
                ],
                "sleep": [
                    {
                        "startDate": "2024-02-11T03:30:00.000Z",
                        "endDate": "2024-02-11T03:30:00.000Z"
                    },
                    {
                        "startDate": "2024-02-11T03:30:00.000Z",
                        "endDate": "2024-02-11T03:30:00.000Z"
                    }
                ],
                "weight": [
                   {
                    "kilograms": 70,
                    "date": "2024-02-11T03:30:00.000Z"
                   },
                   {
                    "kilograms": 70,
                    "date": "2024-02-11T03:30:00.000Z"
                   }
                ],
                "hearthBPM": [
                    {
                        "BPM": 70,
                        "date": "2024-02-11T03:30:00.000Z"
                    },
                    {
                        "BPM": 70,
                        "date": "2024-02-11T03:30:00.000Z"
                    }
                ],
                "ingestedFood": [
                    {
                        "foodName": "Apple",
                        "calories": 150,
                        "date": "2024-02-11T03:30:00.000Z"
                    }
                ]
            }
        },
        {
            "userId": 1,
            "firstName": "Allison",
            "lastName": "Doe",
            "doctors": [3, 4, 5, 6],
            "healthData": {
                "caloriesBurned": [
                    {
                        "calories": 100,
                        "date": "2024-02-11T03:30:00.000Z"
                    },
                    {
                        "calories": 100,
                        "date": "2024-02-11T03:30:00.000Z"
                    }
                ],
                "sleep": [
                    {
                        "startDate": "2024-02-11T03:30:00.000Z",
                        "endDate": "2024-02-11T03:30:00.000Z"
                    },
                    {
                        "startDate": "2024-02-11T03:30:00.000Z",
                        "endDate": "2024-02-11T03:30:00.000Z"
                    }
                ],
                "weight": [
                   {
                    "kilograms": 70,
                    "date": "2024-02-11T03:30:00.000Z"
                   },
                   {
                    "kilograms": 70,
                    "date": "2024-02-11T03:30:00.000Z"
                   }
                ],
                "hearthBPM": [
                    {
                        "BPM": 70,
                        "date": "2024-02-11T03:30:00.000Z"
                    },
                    {
                        "BPM": 70,
                        "date": "2024-02-11T03:30:00.000Z"
                    }
                ],
                "ingestedFood": [
                    {
                        "foodName": "Apple",
                        "calories": 150,
                        "date": "2024-02-11T03:30:00.000Z"
                    }
                ]
            }
        }
    
    ]
}
    